Metadata-Version: 2.1
Name: sdrsac
Version: 0.0.1
Summary: Global and Robust Point Cloud Registration
Home-page: https://github.com/neka-nat/sdrsac
Author: neka-nat
Author-email: nekanat.stock@gmail.com
License: UNKNOWN
Platform: UNKNOWN
